odoo/addons/website_sale_suggest_create_account/README.rst
odoo/addons/website_sale_suggest_create_account/__init__.py
odoo/addons/website_sale_suggest_create_account/__manifest__.py
odoo/addons/website_sale_suggest_create_account/i18n/ca.po
odoo/addons/website_sale_suggest_create_account/i18n/ca_ES.po
odoo/addons/website_sale_suggest_create_account/i18n/de.po
odoo/addons/website_sale_suggest_create_account/i18n/es.po
odoo/addons/website_sale_suggest_create_account/i18n/es_CO.po
odoo/addons/website_sale_suggest_create_account/i18n/fi.po
odoo/addons/website_sale_suggest_create_account/i18n/fr.po
odoo/addons/website_sale_suggest_create_account/i18n/hr.po
odoo/addons/website_sale_suggest_create_account/i18n/it.po
odoo/addons/website_sale_suggest_create_account/i18n/sl.po
odoo/addons/website_sale_suggest_create_account/i18n/website_sale_suggest_create_account.pot
odoo/addons/website_sale_suggest_create_account/readme/CONTRIBUTORS.rst
odoo/addons/website_sale_suggest_create_account/readme/DESCRIPTION.rst
odoo/addons/website_sale_suggest_create_account/readme/USAGE.rst
odoo/addons/website_sale_suggest_create_account/static/description/icon.png
odoo/addons/website_sale_suggest_create_account/static/description/index.html
odoo/addons/website_sale_suggest_create_account/views/website_sale.xml
odoo12_addon_website_sale_suggest_create_account-12.0.1.0.1.dist-info/METADATA
odoo12_addon_website_sale_suggest_create_account-12.0.1.0.1.dist-info/WHEEL
odoo12_addon_website_sale_suggest_create_account-12.0.1.0.1.dist-info/top_level.txt
odoo12_addon_website_sale_suggest_create_account-12.0.1.0.1.dist-info/RECORD
