Metadata-Version: 2.1
Name: odoo12-addon-website-sale-suggest-create-account
Version: 12.0.1.0.1
Summary: Suggest users to create an account when buying in the website
Home-page: https://www.tecnativa.com
Author: Tecnativa, LasLabs, Odoo Community Association (OCA)
Author-email: support@odoo-community.org
License: LGPL-3
Platform: UNKNOWN
Classifier: Programming Language :: Python
Classifier: Framework :: Odoo
Classifier: License :: OSI Approved :: GNU Lesser General Public License v3 (LGPLv3)
Requires-Python: >=3.5
Requires-Dist: odoo (<12.1dev,>=12.0a)
